[{"name":"render_template.action_view","payload":{"identifier":"/Users/kimiboo/workspace/RonR_Eshopper/app/views/admin/categories/index.html.erb","layout":"layouts/cust_admin"},"time":"2017-08-03T11:50:44.786-04:00","transaction_id":"adeccb1ba092b5121b77","end":"2017-08-03T11:50:44.793-04:00","children":[],"duration":7.403},{"name":"render_partial.action_view","payload":{"identifier":"/Users/kimiboo/workspace/RonR_Eshopper/app/views/share/_admin.header.html.erb","cache_hit":null},"time":"2017-08-03T11:50:44.819-04:00","transaction_id":"adeccb1ba092b5121b77","end":"2017-08-03T11:50:44.820-04:00","children":[],"duration":1.397},{"name":"render_partial.action_view","payload":{"identifier":"/Users/kimiboo/workspace/RonR_Eshopper/app/views/share/_admin.sidebar.html.erb","cache_hit":null},"time":"2017-08-03T11:50:44.862-04:00","transaction_id":"adeccb1ba092b5121b77","end":"2017-08-03T11:50:44.864-04:00","children":[],"duration":1.7650000000000001},{"name":"process_action.action_controller","payload":{"controller":"Admin::CategoriesController","action":"index","params":{"controller":"admin/categories","action":"index"},"headers":"Not JSON Encodable","format":"html","method":"GET","path":"/admin/categories","status":200,"view_runtime":81.76400000229478},"time":"2017-08-03T11:50:44.779-04:00","transaction_id":"adeccb1ba092b5121b77","end":"2017-08-03T11:50:44.959-04:00","children":[],"duration":179.82799999999997}]